pms7003/__init__.py
pms7003/pms7003.py
pms7003/pms7003_threading.py
threaded/Pms7003ThreadedReader.py
threaded/__init__.py
threaded/example_threading.py
pms7003-1.1.0.dist-info/LICENSE
pms7003-1.1.0.dist-info/METADATA
pms7003-1.1.0.dist-info/WHEEL
pms7003-1.1.0.dist-info/top_level.txt
pms7003-1.1.0.dist-info/RECORD
