Metadata-Version: 2.1
Name: pms7003
Version: 1.1.0
Summary: A python driver for plantower pms7003 pm sensor
Home-page: https://github.com/tomek-l/pms7003
Author: Tomasz Lewicki
Author-email: t.w.lewicki@gmail.com
License: UNKNOWN
Platform: UNKNOWN
Classifier: Programming Language :: Python :: 3
Classifier: License :: OSI Approved :: MIT License
Classifier: Operating System :: OS Independent
Requires-Python: >=3
Requires-Dist: pyserial
